rodeo/__init__.py
rodeo/rodeo.py
rodeo/utils.py
rodeometric-0.0.1.dist-info/LICENSE
rodeometric-0.0.1.dist-info/METADATA
rodeometric-0.0.1.dist-info/WHEEL
rodeometric-0.0.1.dist-info/top_level.txt
rodeometric-0.0.1.dist-info/RECORD
