Metadata-Version: 2.1
Name: rodeometric
Version: 0.0.1
Summary: Robust Detection Outcome: A Metric for Pathology Detection in Medical Images
Home-page: https://github.com/FeliMe/RoDeO
Author: Felix Meissen, Philip Müller
Author-email: felix.meissen@tum.de, philip.j.mueller@tum.de
License: MIT
Project-URL: Bug Tracker, https://github.com/FeliMe/RoDeO/issues
Project-URL: Source Code, https://github.com/FeliMe/RoDeO
Keywords: deep learning,machine learning,metrics,AI
Classifier: Natural Language :: English
Classifier: License :: OSI Approved :: MIT License
Classifier: Operating System :: OS Independent
Classifier: Intended Audience :: Developers
Classifier: Topic :: Scientific/Engineering :: Artificial Intelligence
Classifier: Programming Language :: Python :: 3
Classifier: Programming Language :: Python :: 3.7
Classifier: Programming Language :: Python :: 3.8
Classifier: Programming Language :: Python :: 3.9
Classifier: Programming Language :: Python :: 3.10
Requires-Python: >=3.7
License-File: LICENSE
Requires-Dist: numpy
Requires-Dist: scipy
Requires-Dist: scikit-learn (>=1.0.2)
